Workbook
Name Slicer_Clean_Category: #N/A
Name Slicer_Clean_Category2: #N/A
Name Slicer_Clean_Region: #N/A
Name Slicer_Clean_Region1: #N/A

Sheet Sales_Performance_Analysis.csv
A1: Order ID | B1: Order Date | C1: Region | D1: Product Category | E1: Sales Amount | F1: Quantity Sold | G1: Discount (%) | H1: Profit | I1: Order ID | J1: Order Date | K1: Clean Region | L1: Clean Category | M1: Sales Amount | N1: Regional Avg Sales | O1: Quantity Sold | P1: Discount (%) | Q1: Profit | S1: Region | T1: Regional Avg Sales | U1: Using TRIM | X1: Using UPPER | AA1: Using LOWER
A2: ab899d2f | B2: 45022 | C2: norTh | D2: groceries | E2: 859.29 | F2: 44 | G2: 37 | H2: 1653.87 | I2: ab899d2f | J2: 45022 | K2: {=_xlfn.IFS(LEFT(C2:C4001,1)="N","North",LEFT(C2:C4001,1)="E","East",LEFT(C2:C4001,1)="M","East",LEFT(C2:C4001,1)="W","West",LEFT(C2:C4001,1)="S","South")} -> North | L2: {=_xlfn.IFS(LEFT(D2:D4001,1)="G","Groceries",LEFT(D2:D4001,1)="C","Clothing",LEFT(D2:D4001,1)="F","Furniture",LEFT(D2:D4001,1)="S","Sports",LEFT(D2:D4001,1)="E","Electronics")} -> Groceries | M2: 859.29 | N2: =VLOOKUP($K2,Sales_Performance_Analysis.csv!$S$1:$T$5,2,FALSE) -> 2573.1196 | O2: 44 | P2: 37 | Q2: 1653.87 | S2: North | T2: =AVERAGEIF(Sales_Performance_Analysis.csv!K:K,"north",Sales_Performance_Analysis.csv!E:E) -> 2573.1196 | U2: {=TRIM(_xlfn.ANCHORARRAY(K2))} -> North | V2: {=TRIM(_xlfn.ANCHORARRAY(L2))} -> Groceries | X2: {=UPPER(_xlfn.ANCHORARRAY(K2))} -> NORTH | Y2: {=UPPER(_xlfn.ANCHORARRAY(L2))} -> GROCERIES | AA2: {=LOWER(_xlfn.ANCHORARRAY(X2))} -> north | AB2: {=LOWER(_xlfn.ANCHORARRAY(Y2))} -> groceries
A3: 73484eb1 | B3: 45412 | C3: Messt | D3: groceries | E3: 1546.81 | F3: 23 | G3: 33 | H3: 1932.71 | I3: 73484eb1 | J3: 45412 | K3: East | L3: Groceries | M3: 1546.81 | N3: =VLOOKUP($K3,Sales_Performance_Analysis.csv!$S$1:$T$5,2,FALSE) -> 2529.8487 | O3: 23 | P3: 33 | Q3: 1932.71 | S3: East | T3: =AVERAGEIF(Sales_Performance_Analysis.csv!K:K,"east",Sales_Performance_Analysis.csv!E:E) -> 2529.8487 | U3: East | V3: Groceries | X3: EAST | Y3: GROCERIES | AA3: east | AB3: groceries
A4: 19395924 | B4: 45363 | C4: eAsT | D4: groceries | E4: 4703.58 | F4: 31 | G4: 15 | H4: 527.47 | I4: 19395924 | J4: 45363 | K4: East | L4: Groceries | M4: 4703.58 | N4: =VLOOKUP($K4,Sales_Performance_Analysis.csv!$S$1:$T$5,2,FALSE) -> 2529.8487 | O4: 31 | P4: 15 | Q4: 527.47 | S4: West | T4: =AVERAGEIF(Sales_Performance_Analysis.csv!K:K,"west",Sales_Performance_Analysis.csv!E:E) -> 2536.311 | U4: East | V4: Groceries | X4: EAST | Y4: GROCERIES | AA4: east | AB4: groceries
A5: b3fded3d | B5: 45331 | C5: eAsT | D5: groceries | E5: 3377.17 | F5: 47 | G5: 3 | H5: 482.65 | I5: b3fded3d | J5: 45331 | K5: East | L5: Groceries | M5: 3377.17 | N5: =VLOOKUP($K5,Sales_Performance_Analysis.csv!$S$1:$T$5,2,FALSE) -> 2529.8487 | O5: 47 | P5: 3 | Q5: 482.65 | S5: South | T5: =AVERAGEIF(Sales_Performance_Analysis.csv!K:K,"south",Sales_Performance_Analysis.csv!E:E) -> 2478.5568 | U5: East | V5: Groceries | X5: EAST | Y5: GROCERIES | AA5: east | AB5: groceries
A6: 6e4bdd51 | B6: 45502 | C6: s0uTH | D6: Clothing | E6: 3517.49 | F6: 6 | G6: 28 | H6: 748.72 | I6: 6e4bdd51 | J6: 45502 | K6: South | L6: Clothing | M6: 3517.49 | N6: =VLOOKUP($K6,Sales_Performance_Analysis.csv!$S$1:$T$5,2,FALSE) -> 2478.5568 | O6: 6 | P6: 28 | Q6: 748.72 | U6: South | V6: Clothing | X6: SOUTH | Y6: CLOTHING | AA6: south | AB6: clothing
A7: 21d88d69 | B7: 45164 | C7: eAsT | D7: FURNiture | E7: 362.55 | F7: 19 | G7: 50 | H7: 314.71 | I7: 21d88d69 | J7: 45164 | K7: East | L7: Furniture | M7: 362.55 | N7: =VLOOKUP($K7,Sales_Performance_Analysis.csv!$S$1:$T$5,2,FALSE) -> 2529.8487 | O7: 19 | P7: 50 | Q7: 314.71 | U7: East | V7: Furniture | X7: EAST | Y7: FURNITURE | AA7: east | AB7: furniture
A8: 9da2704d | B8: 45572 | C8: eAsT | D8: sports | E8: 4811.17 | F8: 22 | G8: 18 | H8: 1372.89 | I8: 9da2704d | J8: 45572 | K8: East | L8: Sports | M8: 4811.17 | N8: =VLOOKUP($K8,Sales_Performance_Analysis.csv!$S$1:$T$5,2,FALSE) -> 2529.8487 | O8: 22 | P8: 18 | Q8: 1372.89 | U8: East | V8: Sports | X8: EAST | Y8: SPORTS | AA8: east | AB8: sports
A9: a1bd6815 | B9: 45000 | C9: Messt | D9: electronicS | E9: 3565.2 | F9: 22 | G9: 16 | H9: 1437.3 | I9: a1bd6815 | J9: 45000 | K9: East | L9: Electronics | M9: 3565.2 | N9: =VLOOKUP($K9,Sales_Performance_Analysis.csv!$S$1:$T$5,2,FALSE) -> 2529.8487 | O9: 22 | P9: 16 | Q9: 1437.3 | U9: East | V9: Electronics | X9: EAST | Y9: ELECTRONICS | AA9: east | AB9: electronics
A10: 0bbd51fc | B10: 45106 | C10: eAsT | D10: Clothing | E10: 3805.25 | F10: 19 | G10: 3 | H10: 1537.28 | I10: 0bbd51fc | J10: 45106 | K10: East | L10: Clothing | M10: 3805.25 | N10: =VLOOKUP($K10,Sales_Performance_Analysis.csv!$S$1:$T$5,2,FALSE) -> 2529.8487 | O10: 19 | P10: 3 | Q10: 1537.28 | U10: East | V10: Clothing | X10: EAST | Y10: CLOTHING | AA10: east | AB10: clothing
A11: 8bf7e4b3 | B11: 44998 | C11: s0uTH | D11: Clothing | E11: 2178.72 | F11: 15 | G11: 24 | H11: 1696.65 | I11: 8bf7e4b3 | J11: 44998 | K11: South | L11: Clothing | M11: 2178.72 | N11: =VLOOKUP($K11,Sales_Performance_Analysis.csv!$S$1:$T$5,2,FALSE) -> 2478.5568 | O11: 15 | P11: 24 | Q11: 1696.65 | U11: South | V11: Clothing | X11: SOUTH | Y11: CLOTHING | AA11: south | AB11: clothing
A12: e6cf1255 | B12: 45439 | C12: Messt | D12: groceries | E12: 2844.93 | F12: 34 | G12: 12 | H12: 1166.39 | I12: e6cf1255 | J12: 45439 | K12: East | L12: Groceries | M12: 2844.93 | N12: =VLOOKUP($K12,Sales_Performance_Analysis.csv!$S$1:$T$5,2,FALSE) -> 2529.8487 | O12: 34 | P12: 12 | Q12: 1166.39 | U12: East | V12: Groceries | X12: EAST | Y12: GROCERIES | AA12: east | AB12: groceries
A13: 3ba1fc5c | B13: 45291 | C13: Messt | D13: electronicS | E13: 3600.04 | F13: 10 | G13: 2 | H13: 1632.75 | I13: 3ba1fc5c | J13: 45291 | K13: East | L13: Electronics | M13: 3600.04 | N13: =VLOOKUP($K13,Sales_Performance_Analysis.csv!$S$1:$T$5,2,FALSE) -> 2529.8487 | O13: 10 | P13: 2 | Q13: 1632.75 | U13: East | V13: Electronics | X13: EAST | Y13: ELECTRONICS | AA13: east | AB13: electronics
A14: 388ff70d | B14: 45239 | C14: eAsT | D14: sports | E14: 941.88 | F14: 13 | G14: 28 | H14: 646.49 | I14: 388ff70d | J14: 45239 | K14: East | L14: Sports | M14: 941.88 | N14: =VLOOKUP($K14,Sales_Performance_Analysis.csv!$S$1:$T$5,2,FALSE) -> 2529.8487 | O14: 13 | P14: 28 | Q14: 646.49 | U14: East | V14: Sports | X14: EAST | Y14: SPORTS | AA14: east | AB14: sports
A15: ce2e9002 | B15: 44919 | C15: s0uTH | D15: sports | E15: 3300.86 | F15: 1 | G15: 48 | H15: 86.9 | I15: ce2e9002 | J15: 44919 | K15: South | L15: Sports | M15: 3300.86 | N15: =VLOOKUP($K15,Sales_Performance_Analysis.csv!$S$1:$T$5,2,FALSE) -> 2478.5568 | O15: 1 | P15: 48 | Q15: 86.9 | U15: South | V15: Sports | X15: SOUTH | Y15: SPORTS | AA15: south | AB15: sports
A16: a4f9a338 | B16: 45329 | C16: eAsT | D16: groceries | E16: 1081.62 | F16: 4 | G16: 19 | H16: 611.06 | I16: a4f9a338 | J16: 45329 | K16: East | L16: Groceries | M16: 1081.62 | N16: =VLOOKUP($K16,Sales_Performance_Analysis.csv!$S$1:$T$5,2,FALSE) -> 2529.8487 | O16: 4 | P16: 19 | Q16: 611.06 | U16: East | V16: Groceries | X16: EAST | Y16: GROCERIES | AA16: east | AB16: groceries
A17: eadceaa8 | B17: 45318 | C17: eAsT | D17: FURNiture | E17: 3455.67 | F17: 39 | G17: 21 | H17: 208.1 | I17: eadceaa8 | J17: 45318 | K17: East | L17: Furniture | M17: 3455.67 | N17: =VLOOKUP($K17,Sales_Performance_Analysis.csv!$S$1:$T$5,2,FALSE) -> 2529.8487 | O17: 39 | P17: 21 | Q17: 208.1 | U17: East | V17: Furniture | X17: EAST | Y17: FURNITURE | AA17: east | AB17: furniture
... A19: 35358e9c | B19: 45471 | C19: norTh | D19: Clothing | E19: 2784.79 | F19: 35 | G19: 40 | H19: 999.6 | I19: 35358e9c | J19: 45471 | K19: North | L19: Clothing | M19: 2784.79 | N19: =VLOOKUP($K19,Sales_Performance_Analysis.csv!$S$1:$T$5,2,FALSE) -> 2573.1196 | O19: 35 | P19: 40 | Q19: 999.6 | U19: North | V19: Clothing | X19: NORTH | Y19: CLOTHING | AA19: north | AB19: clothing
A20: 31676338 | B20: 45246 | C20: s0uTH | D20: Clothing | E20: 1082.98 | F20: 8 | G20: 11 | H20: 1604.19 | I20: 31676338 | J20: 45246 | K20: South | L20: Clothing | M20: 1082.98 | N20: =VLOOKUP($K20,Sales_Performance_Analysis.csv!$S$1:$T$5,2,FALSE) -> 2478.5568 | O20: 8 | P20: 11 | Q20: 1604.19 | U20: South | V20: Clothing | X20: SOUTH | Y20: CLOTHING | AA20: south | AB20: clothing
A21: 05d72e20 | B21: 45556 | C21: eAsT | D21: Clothing | E21: 787.79 | F21: 47 | G21: 18 | H21: 1313.33 | I21: 05d72e20 | J21: 45556 | K21: East | L21: Clothing | M21: 787.79 | N21: =VLOOKUP($K21,Sales_Performance_Analysis.csv!$S$1:$T$5,2,FALSE) -> 2529.8487 | O21: 47 | P21: 18 | Q21: 1313.33 | U21: East | V21: Clothing | X21: EAST | Y21: CLOTHING | AA21: east | AB21: clothing
A22: 68dbe328 | B22: 45566 | C22: s0uTH | D22: FURNiture | E22: 312.7 | F22: 36 | G22: 43 | H22: 559.52 | I22: 68dbe328 | J22: 45566 | K22: South | L22: Furniture | M22: 312.7 | N22: =VLOOKUP($K22,Sales_Performance_Analysis.csv!$S$1:$T$5,2,FALSE) -> 2478.5568 | O22: 36 | P22: 43 | Q22: 559.52 | U22: South | V22: Furniture | X22: SOUTH | Y22: FURNITURE | AA22: south | AB22: furniture
A23: 78d3f47b | B23: 45077 | C23: eAsT | D23: sports | E23: 265.32 | F23: 21 | G23: 36 | H23: 595.91 | I23: 78d3f47b | J23: 45077 | K23: East | L23: Sports | M23: 265.32 | N23: =VLOOKUP($K23,Sales_Performance_Analysis.csv!$S$1:$T$5,2,FALSE) -> 2529.8487 | O23: 21 | P23: 36 | Q23: 595.91 | U23: East | V23: Sports | X23: EAST | Y23: SPORTS | AA23: east | AB23: sports
A24: 9e4d1fe0 | B24: 45400 | C24: Messt | D24: FURNiture | E24: 1253.64 | F24: 35 | G24: 14 | H24: 1653.66 | I24: 9e4d1fe0 | J24: 45400 | K24: East | L24: Furniture | M24: 1253.64 | N24: =VLOOKUP($K24,Sales_Performance_Analysis.csv!$S$1:$T$5,2,FALSE) -> 2529.8487 | O24: 35 | P24: 14 | Q24: 1653.66 | U24: East | V24: Furniture | X24: EAST | Y24: FURNITURE | AA24: east | AB24: furniture
A25: 9215a70e | B25: 45341 | C25: Messt | D25: Clothing | E25: 1874.07 | F25: 28 | G25: 23 | H25: 1783.26 | I25: 9215a70e | J25: 45341 | K25: East | L25: Clothing | M25: 1874.07 | N25: =VLOOKUP($K25,Sales_Performance_Analysis.csv!$S$1:$T$5,2,FALSE) -> 2529.8487 | O25: 28 | P25: 23 | Q25: 1783.26 | U25: East | V25: Clothing | X25: EAST | Y25: CLOTHING | AA25: east | AB25: clothing
A26: 54ca3433 | B26: 45041 | C26: eAsT | D26: Clothing | E26: 2561.71 | F26: 44 | G26: 10 | H26: 800.82 | I26: 54ca3433 | J26: 45041 | K26: East | L26: Clothing | M26: 2561.71 | N26: =VLOOKUP($K26,Sales_Performance_Analysis.csv!$S$1:$T$5,2,FALSE) -> 2529.8487 | O26: 44 | P26: 10 | Q26: 800.82 | U26: East | V26: Clothing | X26: EAST | Y26: CLOTHING | AA26: east | AB26: clothing
A27: 0ba75cc7 | B27: 45059 | C27: Messt | D27: sports | E27: 1960.74 | F27: 50 | G27: 6 | H27: 1530.61 | I27: 0ba75cc7 | J27: 45059 | K27: East | L27: Sports | M27: 1960.74 | N27: =VLOOKUP($K27,Sales_Performance_Analysis.csv!$S$1:$T$5,2,FALSE) -> 2529.8487 | O27: 50 | P27: 6 | Q27: 1530.61 | U27: East | V27: Sports | X27: EAST | Y27: SPORTS | AA27: east | AB27: sports
A28: 601860b1 | B28: 45037 | C28: eAsT | D28: electronicS | E28: 2415.44 | F28: 35 | G28: 14 | H28: 335.57 | I28: 601860b1 | J28: 45037 | K28: East | L28: Electronics | M28: 2415.44 | N28: =VLOOKUP($K28,Sales_Performance_Analysis.csv!$S$1:$T$5,2,FALSE) -> 2529.8487 | O28: 35 | P28: 14 | Q28: 335.57 | U28: East | V28: Electronics | X28: EAST | Y28: ELECTRONICS | AA28: east | AB28: electronics
A29: e393e106 | B29: 45290 | C29: eAsT | D29: electronicS | E29: 2284.22 | F29: 8 | G29: 41 | H29: 1866.59 | I29: e393e106 | J29: 45290 | K29: East | L29: Electronics | M29: 2284.22 | N29: =VLOOKUP($K29,Sales_Performance_Analysis.csv!$S$1:$T$5,2,FALSE) -> 2529.8487 | O29: 8 | P29: 41 | Q29: 1866.59 | U29: East | V29: Electronics | X29: EAST | Y29: ELECTRONICS | AA29: east | AB29: electronics
A30: 7ab3d472 | B30: 44885 | C30: Messt | D30: sports | E30: 2118.55 | F30: 29 | G30: 24 | H30: 702.15 | I30: 7ab3d472 | J30: 44885 | K30: East | L30: Sports | M30: 2118.55 | N30: =VLOOKUP($K30,Sales_Performance_Analysis.csv!$S$1:$T$5,2,FALSE) -> 2529.8487 | O30: 29 | P30: 24 | Q30: 702.15 | U30: East | V30: Sports | X30: EAST | Y30: SPORTS | AA30: east | AB30: sports
A31: 01d9b1ae | B31: 45248 | C31: s0uTH | D31: groceries | E31: 4803.6 | F31: 11 | G31: 12 | H31: 1086.74 | I31: 01d9b1ae | J31: 45248 | K31: South | L31: Groceries | M31: 4803.6 | N31: =VLOOKUP($K31,Sales_Performance_Analysis.csv!$S$1:$T$5,2,FALSE) -> 2478.5568 | O31: 11 | P31: 12 | Q31: 1086.74 | U31: South | V31: Groceries | X31: SOUTH | Y31: GROCERIES | AA31: south | AB31: groceries
A32: 20385cb6 | B32: 45533 | C32: norTh | D32: groceries | E32: 4297 | F32: 17 | G32: 49 | H32: 678.7 | I32: 20385cb6 | J32: 45533 | K32: North | L32: Groceries | M32: 4297 | N32: =VLOOKUP($K32,Sales_Performance_Analysis.csv!$S$1:$T$5,2,FALSE) -> 2573.1196 | O32: 17 | P32: 49 | Q32: 678.7 | U32: North | V32: Groceries | X32: NORTH | Y32: GROCERIES | AA32: north | AB32: groceries
... A69: 92458ed3 | B69: 45024 | C69: norTh | D69: FURNiture | E69: 1356.62 | F69: 2 | G69: 21 | H69: 1213.34 | I69: 92458ed3 | J69: 45024 | K69: North | L69: Furniture | M69: 1356.62 | N69: =VLOOKUP($K69,Sales_Performance_Analysis.csv!$S$1:$T$5,2,FALSE) -> 2573.1196 | O69: 2 | P69: 21 | Q69: 1213.34 | U69: North | V69: Furniture | X69: NORTH | Y69: FURNITURE | AA69: north | AB69: furniture
A70: 76740552 | B70: 45201 | C70: s0uTH | D70: electronicS | E70: 2905.8 | F70: 20 | G70: 10 | H70: 1417.43 | I70: 76740552 | J70: 45201 | K70: South | L70: Electronics | M70: 2905.8 | N70: =VLOOKUP($K70,Sales_Performance_Analysis.csv!$S$1:$T$5,2,FALSE) -> 2478.5568 | O70: 20 | P70: 10 | Q70: 1417.43 | U70: South | V70: Electronics | X70: SOUTH | Y70: ELECTRONICS | AA70: south | AB70: electronics
A71: f92de80d | B71: 45060 | C71: s0uTH | D71: FURNiture | E71: 2065.42 | F71: 22 | G71: 15 | H71: 787.51 | I71: f92de80d | J71: 45060 | K71: South | L71: Furniture | M71: 2065.42 | N71: =VLOOKUP($K71,Sales_Performance_Analysis.csv!$S$1:$T$5,2,FALSE) -> 2478.5568 | O71: 22 | P71: 15 | Q71: 787.51 | U71: South | V71: Furniture | X71: SOUTH | Y71: FURNITURE | AA71: south | AB71: furniture
A72: 647ff51a | B72: 45094 | C72: eAsT | D72: Clothing | E72: 272.88 | F72: 47 | G72: 29 | H72: 1208.68 | I72: 647ff51a | J72: 45094 | K72: East | L72: Clothing | M72: 272.88 | N72: =VLOOKUP($K72,Sales_Performance_Analysis.csv!$S$1:$T$5,2,FALSE) -> 2529.8487 | O72: 47 | P72: 29 | Q72: 1208.68 | U72: East | V72: Clothing | X72: EAST | Y72: CLOTHING | AA72: east | AB72: clothing
A73: f8548ec7 | B73: 45594 | C73: eAsT | D73: Clothing | E73: 4126.4 | F73: 34 | G73: 13 | H73: 1690.11 | I73: f8548ec7 | J73: 45594 | K73: East | L73: Clothing | M73: 4126.4 | N73: =VLOOKUP($K73,Sales_Performance_Analysis.csv!$S$1:$T$5,2,FALSE) -> 2529.8487 | O73: 34 | P73: 13 | Q73: 1690.11 | U73: East | V73: Clothing | X73: EAST | Y73: CLOTHING | AA73: east | AB73: clothing
A74: 7855a0d2 | B74: 45195 | C74: norTh | D74: FURNiture | E74: 4204.55 | F74: 49 | G74: 1 | H74: 1534.82 | I74: 7855a0d2 | J74: 45195 | K74: North | L74: Furniture | M74: 4204.55 | N74: =VLOOKUP($K74,Sales_Performance_Analysis.csv!$S$1:$T$5,2,FALSE) -> 2573.1196 | O74: 49 | P74: 1 | Q74: 1534.82 | U74: North | V74: Furniture | X74: NORTH | Y74: FURNITURE | AA74: north | AB74: furniture
A75: bf586512 | B75: 45226 | C75: Messt | D75: Clothing | E75: 2130.98 | F75: 7 | G75: 29 | H75: 679.16 | I75: bf586512 | J75: 45226 | K75: East | L75: Clothing | M75: 2130.98 | N75: =VLOOKUP($K75,Sales_Performance_Analysis.csv!$S$1:$T$5,2,FALSE) -> 2529.8487 | O75: 7 | P75: 29 | Q75: 679.16 | U75: East | V75: Clothing | X75: EAST | Y75: CLOTHING | AA75: east | AB75: clothing
A76: deea1965 | B76: 45436 | C76: s0uTH | D76: FURNiture | E76: 1253.28 | F76: 4 | G76: 48 | H76: 317.33 | I76: deea1965 | J76: 45436 | K76: South | L76: Furniture | M76: 1253.28 | N76: =VLOOKUP($K76,Sales_Performance_Analysis.csv!$S$1:$T$5,2,FALSE) -> 2478.5568 | O76: 4 | P76: 48 | Q76: 317.33 | U76: South | V76: Furniture | X76: SOUTH | Y76: FURNITURE | AA76: south | AB76: furniture
A77: a0a8290f | B77: 45478 | C77: s0uTH | D77: sports | E77: 1050.29 | F77: 30 | G77: 4 | H77: 423.5 | I77: a0a8290f | J77: 45478 | K77: South | L77: Sports | M77: 1050.29 | N77: =VLOOKUP($K77,Sales_Performance_Analysis.csv!$S$1:$T$5,2,FALSE) -> 2478.5568 | O77: 30 | P77: 4 | Q77: 423.5 | U77: South | V77: Sports | X77: SOUTH | Y77: SPORTS | AA77: south | AB77: sports
A78: 077a9429 | B78: 45079 | C78: norTh | D78: FURNiture | E78: 1269.1 | F78: 3 | G78: 7 | H78: 1819.88 | I78: 077a9429 | J78: 45079 | K78: North | L78: Furniture | M78: 1269.1 | N78: =VLOOKUP($K78,Sales_Performance_Analysis.csv!$S$1:$T$5,2,FALSE) -> 2573.1196 | O78: 3 | P78: 7 | Q78: 1819.88 | U78: North | V78: Furniture | X78: NORTH | Y78: FURNITURE | AA78: north | AB78: furniture
A79: 8642940000 | B79: 45192 | C79: Messt | D79: Groceries | E79: 4229.47 | F79: 3 | G79: 9 | H79: 11.29 | I79: 8642940000 | J79: 45192 | K79: East | L79: Groceries | M79: 4229.47 | N79: =VLOOKUP($K79,Sales_Performance_Analysis.csv!$S$1:$T$5,2,FALSE) -> 2529.8487 | O79: 3 | P79: 9 | Q79: 11.29 | U79: East | V79: Groceries | X79: EAST | Y79: GROCERIES | AA79: east | AB79: groceries
A80: 41d1321a | B80: 45243 | C80: s0uTH | D80: Groceries | E80: 3767.63 | F80: 30 | G80: 41 | H80: 1031.74 | I80: 41d1321a | J80: 45243 | K80: South | L80: Groceries | M80: 3767.63 | N80: =VLOOKUP($K80,Sales_Performance_Analysis.csv!$S$1:$T$5,2,FALSE) -> 2478.5568 | O80: 30 | P80: 41 | Q80: 1031.74 | U80: South | V80: Groceries | X80: SOUTH | Y80: GROCERIES | AA80: south | AB80: groceries
A81: 44afa795 | B81: 45068 | C81: Messt | D81: sports | E81: 640.91 | F81: 19 | G81: 19 | H81: 1148.62 | I81: 44afa795 | J81: 45068 | K81: East | L81: Sports | M81: 640.91 | N81: =VLOOKUP($K81,Sales_Performance_Analysis.csv!$S$1:$T$5,2,FALSE) -> 2529.8487 | O81: 19 | P81: 19 | Q81: 1148.62 | U81: East | V81: Sports | X81: EAST | Y81: SPORTS | AA81: east | AB81: sports
A82: 8c329e53 | B82: 45461 | C82: norTh | D82: FURNiture | E82: 2958 | F82: 4 | G82: 22 | H82: 1968.62 | I82: 8c329e53 | J82: 45461 | K82: North | L82: Furniture | M82: 2958 | N82: =VLOOKUP($K82,Sales_Performance_Analysis.csv!$S$1:$T$5,2,FALSE) -> 2573.1196 | O82: 4 | P82: 22 | Q82: 1968.62 | U82: North | V82: Furniture | X82: NORTH | Y82: FURNITURE | AA82: north | AB82: furniture
A83: cdbba08a | B83: 44948 | C83: Messt | D83: sports | E83: 4049.49 | F83: 5 | G83: 1 | H83: 1151.9 | I83: cdbba08a | J83: 44948 | K83: East | L83: Sports | M83: 4049.49 | N83: =VLOOKUP($K83,Sales_Performance_Analysis.csv!$S$1:$T$5,2,FALSE) -> 2529.8487 | O83: 5 | P83: 1 | Q83: 1151.9 | U83: East | V83: Sports | X83: EAST | Y83: SPORTS | AA83: east | AB83: sports
A84: 4415c908 | B84: 45385 | C84: norTh | D84: sports | E84: 4155.03 | F84: 32 | G84: 5 | H84: 1637.7 | I84: 4415c908 | J84: 45385 | K84: North | L84: Sports | M84: 4155.03 | N84: =VLOOKUP($K84,Sales_Performance_Analysis.csv!$S$1:$T$5,2,FALSE) -> 2573.1196 | O84: 32 | P84: 5 | Q84: 1637.7 | U84: North | V84: Sports | X84: NORTH | Y84: SPORTS | AA84: north | AB84: sports
A85: a9ac13d3 | B85: 45556 | C85: norTh | D85: FURNiture | E85: 2011.35 | F85: 44 | G85: 10 | H85: 829.69 | I85: a9ac13d3 | J85: 45556 | K85: North | L85: Furniture | M85: 2011.35 | N85: =VLOOKUP($K85,Sales_Performance_Analysis.csv!$S$1:$T$5,2,FALSE) -> 2573.1196 | O85: 44 | P85: 10 | Q85: 829.69 | U85: North | V85: Furniture | X85: NORTH | Y85: FURNITURE | AA85: north | AB85: furniture
A86: 5fbf219e | B86: 45299 | C86: Messt | D86: electronicS | E86: 2365.24 | F86: 10 | G86: 33 | H86: 1970.1 | I86: 5fbf219e | J86: 45299 | K86: East | L86: Electronics | M86: 2365.24 | N86: =VLOOKUP($K86,Sales_Performance_Analysis.csv!$S$1:$T$5,2,FALSE) -> 2529.8487 | O86: 10 | P86: 33 | Q86: 1970.1 | U86: East | V86: Electronics | X86: EAST | Y86: ELECTRONICS | AA86: east | AB86: electronics
A87: f3ba50cf | B87: 45321 | C87: s0uTH | D87: Clothing | E87: 2615.84 | F87: 31 | G87: 9 | H87: 1276.87 | I87: f3ba50cf | J87: 45321 | K87: South | L87: Clothing | M87: 2615.84 | N87: =VLOOKUP($K87,Sales_Performance_Analysis.csv!$S$1:$T$5,2,FALSE) -> 2478.5568 | O87: 31 | P87: 9 | Q87: 1276.87 | U87: South | V87: Clothing | X87: SOUTH | Y87: CLOTHING | AA87: south | AB87: clothing
A88: 88840b0f | B88: 45399 | C88: Messt | D88: Clothing | E88: 4954.33 | F88: 26 | G88: 43 | H88: 1723.31 | I88: 88840b0f | J88: 45399 | K88: East | L88: Clothing | M88: 4954.33 | N88: =VLOOKUP($K88,Sales_Performance_Analysis.csv!$S$1:$T$5,2,FALSE) -> 2529.8487 | O88: 26 | P88: 43 | Q88: 1723.31 | U88: East | V88: Clothing | X88: EAST | Y88: CLOTHING | AA88: east | AB88: clothing
A89: 3dcffe93 | B89: 45082 | C89: norTh | D89: Clothing | E89: 1969.35 | F89: 27 | G89: 11 | H89: 1532.9 | I89: 3dcffe93 | J89: 45082 | K89: North | L89: Clothing | M89: 1969.35 | N89: =VLOOKUP($K89,Sales_Performance_Analysis.csv!$S$1:$T$5,2,FALSE) -> 2573.1196 | O89: 27 | P89: 11 | Q89: 1532.9 | U89: North | V89: Clothing | X89: NORTH | Y89: CLOTHING | AA89: north | AB89: clothing
A90: 745eb905 | B90: 45383 | C90: norTh | D90: Clothing | E90: 2083.02 | F90: 49 | G90: 11 | H90: 105.26 | I90: 745eb905 | J90: 45383 | K90: North | L90: Clothing | M90: 2083.02 | N90: =VLOOKUP($K90,Sales_Performance_Analysis.csv!$S$1:$T$5,2,FALSE) -> 2573.1196 | O90: 49 | P90: 11 | Q90: 105.26 | U90: North | V90: Clothing | X90: NORTH | Y90: CLOTHING | AA90: north | AB90: clothing
A91: b8fca939 | B91: 45530 | C91: s0uTH | D91: electronicS | E91: 4752.49 | F91: 36 | G91: 8 | H91: 1903.35 | I91: b8fca939 | J91: 45530 | K91: South | L91: Electronics | M91: 4752.49 | N91: =VLOOKUP($K91,Sales_Performance_Analysis.csv!$S$1:$T$5,2,FALSE) -> 2478.5568 | O91: 36 | P91: 8 | Q91: 1903.35 | U91: South | V91: Electronics | X91: SOUTH | Y91: ELECTRONICS | AA91: south | AB91: electronics
... A150: c41efe4c | B150: 45434 | C150: s0uTH | D150: FURNiture | E150: 1453.8 | F150: 13 | G150: 16 | H150: 385.22 | I150: c41efe4c | J150: 45434 | K150: South | L150: Furniture | M150: 1453.8 | N150: =VLOOKUP($K150,Sales_Performance_Analysis.csv!$S$1:$T$5,2,FALSE) -> 2478.5568 | O150: 13 | P150: 16 | Q150: 385.22 | U150: South | V150: Furniture | X150: SOUTH | Y150: FURNITURE | AA150: south | AB150: furniture
A151: 61831599 | B151: 44923 | C151: eAsT | D151: sports | E151: 4889.46 | F151: 1 | G151: 20 | H151: 807.13 | I151: 61831599 | J151: 44923 | K151: East | L151: Sports | M151: 4889.46 | N151: =VLOOKUP($K151,Sales_Performance_Analysis.csv!$S$1:$T$5,2,FALSE) -> 2529.8487 | O151: 1 | P151: 20 | Q151: 807.13 | U151: East | V151: Sports | X151: EAST | Y151: SPORTS | AA151: east | AB151: sports
A152: cf159d42 | B152: 45106 | C152: eAsT | D152: sports | E152: 2548.91 | F152: 3 | G152: 7 | H152: 694.24 | I152: cf159d42 | J152: 45106 | K152: East | L152: Sports | M152: 2548.91 | N152: =VLOOKUP($K152,Sales_Performance_Analysis.csv!$S$1:$T$5,2,FALSE) -> 2529.8487 | O152: 3 | P152: 7 | Q152: 694.24 | U152: East | V152: Sports | X152: EAST | Y152: SPORTS | AA152: east | AB152: sports
A153: ffa6342d | B153: 45144 | C153: s0uTH | D153: Clothing | E153: 3804.77 | F153: 31 | G153: 47 | H153: 185.46 | I153: ffa6342d | J153: 45144 | K153: South | L153: Clothing | M153: 3804.77 | N153: =VLOOKUP($K153,Sales_Performance_Analysis.csv!$S$1:$T$5,2,FALSE) -> 2478.5568 | O153: 31 | P153: 47 | Q153: 185.46 | U153: South | V153: Clothing | X153: SOUTH | Y153: CLOTHING | AA153: south | AB153: clothing
A154: 459360d4 | B154: 45499 | C154: eAsT | D154: Groceries | E154: 372.53 | F154: 19 | G154: 13 | H154: 232.82 | I154: 459360d4 | J154: 45499 | K154: East | L154: Groceries | M154: 372.53 | N154: =VLOOKUP($K154,Sales_Performance_Analysis.csv!$S$1:$T$5,2,FALSE) -> 2529.8487 | O154: 19 | P154: 13 | Q154: 232.82 | U154: East | V154: Groceries | X154: EAST | Y154: GROCERIES | AA154: east | AB154: groceries
A155: fdf4755a | B155: 45497 | C155: norTh | D155: electronicS | E155: 2573.55 | F155: 48 | G155: 36 | H155: 1707.54 | I155: fdf4755a | J155: 45497 | K155: North | L155: Electronics | M155: 2573.55 | N155: =VLOOKUP($K155,Sales_Performance_Analysis.csv!$S$1:$T$5,2,FALSE) -> 2573.1196 | O155: 48 | P155: 36 | Q155: 1707.54 | U155: North | V155: Electronics | X155: NORTH | Y155: ELECTRONICS | AA155: north | AB155: electronics
A156: 0a7d436c | B156: 45235 | C156: Messt | D156: Clothing | E156: 1761.29 | F156: 27 | G156: 12 | H156: 492.03 | I156: 0a7d436c | J156: 45235 | K156: East | L156: Clothing | M156: 1761.29 | N156: =VLOOKUP($K156,Sales_Performance_Analysis.csv!$S$1:$T$5,2,FALSE) -> 2529.8487 | O156: 27 | P156: 12 | Q156: 492.03 | U156: East | V156: Clothing | X156: EAST | Y156: CLOTHING | AA156: east | AB156: clothing
A157: 3c1ab674 | B157: 44972 | C157: eAsT | D157: GrocerieS | E157: 4113.4 | F157: 32 | G157: 3 | H157: 1726.09 | I157: 3c1ab674 | J157: 44972 | K157: East | L157: Groceries | M157: 4113.4 | N157: =VLOOKUP($K157,Sales_Performance_Analysis.csv!$S$1:$T$5,2,FALSE) -> 2529.8487 | O157: 32 | P157: 3 | Q157: 1726.09 | U157: East | V157: Groceries | X157: EAST | Y157: GROCERIES | AA157: east | AB157: groceries
A158: 42b5d016 | B158: 45147 | C158: Messt | D158: electronicS | E158: 202.21 | F158: 6 | G158: 43 | H158: 734.47 | I158: 42b5d016 | J158: 45147 | K158: East | L158: Electronics | M158: 202.21 | N158: =VLOOKUP($K158,Sales_Performance_Analysis.csv!$S$1:$T$5,2,FALSE) -> 2529.8487 | O158: 6 | P158: 43 | Q158: 734.47 | U158: East | V158: Electronics | X158: EAST | Y158: ELECTRONICS | AA158: east | AB158: electronics
A159: 2616d5b4 | B159: 45576 | C159: norTh | D159: sports | E159: 4347.15 | F159: 20 | G159: 34 | H159: 1392.45 | I159: 2616d5b4 | J159: 45576 | K159: North | L159: Sports | M159: 4347.15 | N159: =VLOOKUP($K159,Sales_Performance_Analysis.csv!$S$1:$T$5,2,FALSE) -> 2573.1196 | O159: 20 | P159: 34 | Q159: 1392.45 | U159: North | V159: Sports | X159: NORTH | Y159: SPORTS | AA159: north | AB159: sports
A160: 338c4722 | B160: 45364 | C160: Messt | D160: Clothing | E160: 4992.83 | F160: 2 | G160: 28 | H160: 1468.94 | I160: 338c4722 | J160: 45364 | K160: East | L160: Clothing | M160: 4992.83 | N160: =VLOOKUP($K160,Sales_Performance_Analysis.csv!$S$1:$T$5,2,FALSE) -> 2529.8487 | O160: 2 | P160: 28 | Q160: 1468.94 | U160: East | V160: Clothing | X160: EAST | Y160: CLOTHING | AA160: east | AB160: clothing
A161: 6b1e9797 | B161: 45500 | C161: eAsT | D161: sports | E161: 1387.18 | F161: 28 | G161: 9 | H161: 381.96 | I161: 6b1e9797 | J161: 45500 | K161: East | L161: Sports | M161: 1387.18 | N161: =VLOOKUP($K161,Sales_Performance_Analysis.csv!$S$1:$T$5,2,FALSE) -> 2529.8487 | O161: 28 | P161: 9 | Q161: 381.96 | U161: East | V161: Sports | X161: EAST | Y161: SPORTS | AA161: east | AB161: sports
A162: 6e4fab78 | B162: 45566 | C162: norTh | D162: Clothing | E162: 4642.87 | F162: 35 | G162: 14 | H162: 216.96 | I162: 6e4fab78 | J162: 45566 | K162: North | L162: Clothing | M162: 4642.87 | N162: =VLOOKUP($K162,Sales_Performance_Analysis.csv!$S$1:$T$5,2,FALSE) -> 2573.1196 | O162: 35 | P162: 14 | Q162: 216.96 | U162: North | V162: Clothing | X162: NORTH | Y162: CLOTHING | AA162: north | AB162: clothing
A163: 8944bc68 | B163: 45165 | C163: eAsT | D163: electronicS | E163: 4879.9 | F163: 37 | G163: 5 | H163: 1424.1 | I163: 8944bc68 | J163: 45165 | K163: East | L163: Electronics | M163: 4879.9 | N163: =VLOOKUP($K163,Sales_Performance_Analysis.csv!$S$1:$T$5,2,FALSE) -> 2529.8487 | O163: 37 | P163: 5 | Q163: 1424.1 | U163: East | V163: Electronics | X163: EAST | Y163: ELECTRONICS | AA163: east | AB163: electronics
... A199: 1e18c00a | B199: 44931 | C199: norTh | D199: Clothing | E199: 2925.27 | F199: 24 | G199: 4 | H199: 1753.87 | I199: 1e18c00a | J199: 44931 | K199: North | L199: Clothing | M199: 2925.27 | N199: =VLOOKUP($K199,Sales_Performance_Analysis.csv!$S$1:$T$5,2,FALSE) -> 2573.1196 | O199: 24 | P199: 4 | Q199: 1753.87 | U199: North | V199: Clothing | X199: NORTH | Y199: CLOTHING | AA199: north | AB199: clothing
A200: 37431000 | B200: 45161 | C200: s0uTH | D200: GrocerieS | E200: 2454.67 | F200: 10 | G200: 28 | H200: 47.54 | I200: 37431000 | J200: 45161 | K200: South | L200: Groceries | M200: 2454.67 | N200: =VLOOKUP($K200,Sales_Performance_Analysis.csv!$S$1:$T$5,2,FALSE) -> 2478.5568 | O200: 10 | P200: 28 | Q200: 47.54 | U200: South | V200: Groceries | X200: SOUTH | Y200: GROCERIES | AA200: south | AB200: groceries
A201: af24551a | B201: 45040 | C201: norTh | D201: GrocerieS | E201: 4662.47 | F201: 13 | G201: 22 | H201: 735.39 | I201: af24551a | J201: 45040 | K201: North | L201: Groceries | M201: 4662.47 | N201: =VLOOKUP($K201,Sales_Performance_Analysis.csv!$S$1:$T$5,2,FALSE) -> 2573.1196 | O201: 13 | P201: 22 | Q201: 735.39 | U201: North | V201: Groceries | X201: NORTH | Y201: GROCERIES | AA201: north | AB201: groceries
A202: 6b389c40 | B202: 45113 | C202: Messt | D202: Clothing | E202: 2943.33 | F202: 45 | G202: 8 | H202: 571.04 | I202: 6b389c40 | J202: 45113 | K202: East | L202: Clothing | M202: 2943.33 | N202: =VLOOKUP($K202,Sales_Performance_Analysis.csv!$S$1:$T$5,2,FALSE) -> 2529.8487 | O202: 45 | P202: 8 | Q202: 571.04 | U202: East | V202: Clothing | X202: EAST | Y202: CLOTHING | AA202: east | AB202: clothing
A203: 7743bcd0 | B203: 45022 | C203: s0uTH | D203: GrocerieS | E203: 2261.46 | F203: 46 | G203: 39 | H203: 373.45 | I203: 7743bcd0 | J203: 45022 | K203: South | L203: Groceries | M203: 2261.46 | N203: =VLOOKUP($K203,Sales_Performance_Analysis.csv!$S$1:$T$5,2,FALSE) -> 2478.5568 | O203: 46 | P203: 39 | Q203: 373.45 | U203: South | V203: Groceries | X203: SOUTH | Y203: GROCERIES | AA203: south | AB203: groceries
A204: 84d09672 | B204: 45180 | C204: norTh | D204: sports | E204: 2679.53 | F204: 36 | G204: 6 | H204: 1471 | I204: 84d09672 | J204: 45180 | K204: North | L204: Sports | M204: 2679.53 | N204: =VLOOKUP($K204,Sales_Performance_Analysis.csv!$S$1:$T$5,2,FALSE) -> 2573.1196 | O204: 36 | P204: 6 | Q204: 1471 | U204: North | V204: Sports | X204: NORTH | Y204: SPORTS | AA204: north | AB204: sports
A205: bd554f96 | B205: 45011 | C205: eAsT | D205: electronicS | E205: 1290.66 | F205: 46 | G205: 8 | H205: 147.39 | I205: bd554f96 | J205: 45011 | K205: East | L205: Electronics | M205: 1290.66 | N205: =VLOOKUP($K205,Sales_Performance_Analysis.csv!$S$1:$T$5,2,FALSE) -> 2529.8487 | O205: 46 | P205: 8 | Q205: 147.39 | U205: East | V205: Electronics | X205: EAST | Y205: ELECTRONICS | AA205: east | AB205: electronics
A206: dee8766b | B206: 45410 | C206: eAsT | D206: GrocerieS | E206: 211.31 | F206: 45 | G206: 48 | H206: 1844.45 | I206: dee8766b | J206: 45410 | K206: East | L206: Groceries | M206: 211.31 | N206: =VLOOKUP($K206,Sales_Performance_Analysis.csv!$S$1:$T$5,2,FALSE) -> 2529.8487 | O206: 45 | P206: 48 | Q206: 1844.45 | U206: East | V206: Groceries | X206: EAST | Y206: GROCERIES | AA206: east | AB206: groceries
A207: 733628ca | B207: 45310 | C207: Messt | D207: FURNiture | E207: 3582.85 | F207: 42 | G207: 48 | H207: 1359.36 | I207: 733628ca | J207: 45310 | K207: East | L207: Furniture | M207: 3582.85 | N207: =VLOOKUP($K207,Sales_Performance_Analysis.csv!$S$1:$T$5,2,FALSE) -> 2529.8487 | O207: 42 | P207: 48 | Q207: 1359.36 | U207: East | V207: Furniture | X207: EAST | Y207: FURNITURE | AA207: east | AB207: furniture
A208: 7101a707 | B208: 45097 | C208: Messt | D208: FURNiture | E208: 419.94 | F208: 12 | G208: 22 | H208: 1047.8 | I208: 7101a707 | J208: 45097 | K208: East | L208: Furniture | M208: 419.94 | N208: =VLOOKUP($K208,Sales_Performance_Analysis.csv!$S$1:$T$5,2,FALSE) -> 2529.8487 | O208: 12 | P208: 22 | Q208: 1047.8 | U208: East | V208: Furniture | X208: EAST | Y208: FURNITURE | AA208: east | AB208: furniture
A209: 7349ac4e | B209: 45259 | C209: eAsT | D209: sports | E209: 4422.18 | F209: 14 | G209: 33 | H209: 237.47 | I209: 7349ac4e | J209: 45259 | K209: East | L209: Sports | M209: 4422.18 | N209: =VLOOKUP($K209,Sales_Performance_Analysis.csv!$S$1:$T$5,2,FALSE) -> 2529.8487 | O209: 14 | P209: 33 | Q209: 237.47 | U209: East | V209: Sports | X209: EAST | Y209: SPORTS | AA209: east | AB209: sports
A210: fbe74fbe | B210: 44907 | C210: eAsT | D210: FURNiture | E210: 3277.47 | F210: 11 | G210: 2 | H210: 379.92 | I210: fbe74fbe | J210: 44907 | K210: East | L210: Furniture | M210: 3277.47 | N210: =VLOOKUP($K210,Sales_Performance_Analysis.csv!$S$1:$T$5,2,FALSE) -> 2529.8487 | O210: 11 | P210: 2 | Q210: 379.92 | U210: East | V210: Furniture | X210: EAST | Y210: FURNITURE | AA210: east | AB210: furniture
A211: 6bde908c | B211: 45524 | C211: norTh | D211: Clothing | E211: 4264.38 | F211: 31 | G211: 24 | H211: 1179.93 | I211: 6bde908c | J211: 45524 | K211: North | L211: Clothing | M211: 4264.38 | N211: =VLOOKUP($K211,Sales_Performance_Analysis.csv!$S$1:$T$5,2,FALSE) -> 2573.1196 | O211: 31 | P211: 24 | Q211: 1179.93 | U211: North | V211: Clothing | X211: NORTH | Y211: CLOTHING | AA211: north | AB211: clothing
A212: 56a98641 | B212: 45016 | C212: s0uTH | D212: FURNiture | E212: 647.38 | F212: 16 | G212: 34 | H212: 1937.88 | I212: 56a98641 | J212: 45016 | K212: South | L212: Furniture | M212: 647.38 | N212: =VLOOKUP($K212,Sales_Performance_Analysis.csv!$S$1:$T$5,2,FALSE) -> 2478.5568 | O212: 16 | P212: 34 | Q212: 1937.88 | U212: South | V212: Furniture | X212: SOUTH | Y212: FURNITURE | AA212: south | AB212: furniture
... A216: 2ecc60c1 | B216: 44934 | C216: s0uTH | D216: Clothing | E216: 4559.22 | F216: 14 | G216: 29 | H216: 1055.86 | I216: 2ecc60c1 | J216: 44934 | K216: South | L216: Clothing | M216: 4559.22 | N216: =VLOOKUP($K216,Sales_Performance_Analysis.csv!$S$1:$T$5,2,FALSE) -> 2478.5568 | O216: 14 | P216: 29 | Q216: 1055.86 | U216: South | V216: Clothing | X216: SOUTH | Y216: CLOTHING | AA216: south | AB216: clothing
A217: 60839616 | B217: 45529 | C217: s0uTH | D217: sports | E217: 1787.05 | F217: 11 | G217: 19 | H217: 40.81 | I217: 60839616 | J217: 45529 | K217: South | L217: Sports | M217: 1787.05 | N217: =VLOOKUP($K217,Sales_Performance_Analysis.csv!$S$1:$T$5,2,FALSE) -> 2478.5568 | O217: 11 | P217: 19 | Q217: 40.81 | U217: South | V217: Sports | X217: SOUTH | Y217: SPORTS | AA217: south | AB217: sports
A218: a65dfe8b | B218: 45104 | C218: Messt | D218: FURNiture | E218: 901.68 | F218: 7 | G218: 48 | H218: 903.11 | I218: a65dfe8b | J218: 45104 | K218: East | L218: Furniture | M218: 901.68 | N218: =VLOOKUP($K218,Sales_Performance_Analysis.csv!$S$1:$T$5,2,FALSE) -> 2529.8487 | O218: 7 | P218: 48 | Q218: 903.11 | U218: East | V218: Furniture | X218: EAST | Y218: FURNITURE | AA218: east | AB218: furniture
A219: 850b0c26 | B219: 45423 | C219: norTh | D219: electronicS | E219: 2934.72 | F219: 20 | G219: 12 | H219: 528.02 | I219: 850b0c26 | J219: 45423 | K219: North | L219: Electronics | M219: 2934.72 | N219: =VLOOKUP($K219,Sales_Performance_Analysis.csv!$S$1:$T$5,2,FALSE) -> 2573.1196 | O219: 20 | P219: 12 | Q219: 528.02 | U219: North | V219: Electronics | X219: NORTH | Y219: ELECTRONICS | AA219: north | AB219: electronics
A220: 21fd10ea | B220: 45388 | C220: Messt | D220: GrocerieS | E220: 1058.57 | F220: 6 | G220: 13 | H220: 697.72 | I220: 21fd10ea | J220: 45388 | K220: East | L220: Groceries | M220: 1058.57 | N220: =VLOOKUP($K220,Sales_Performance_Analysis.csv!$S$1:$T$5,2,FALSE) -> 2529.8487 | O220: 6 | P220: 13 | Q220: 697.72 | U220: East | V220: Groceries | X220: EAST | Y220: GROCERIES | AA220: east | AB220: groceries
A221: 8d90e130 | B221: 44965 | C221: eAsT | D221: FURNiture | E221: 3988.42 | F221: 36 | G221: 1 | H221: 1637.88 | I221: 8d90e130 | J221: 44965 | K221: East | L221: Furniture | M221: 3988.42 | N221: =VLOOKUP($K221,Sales_Performance_Analysis.csv!$S$1:$T$5,2,FALSE) -> 2529.8487 | O221: 36 | P221: 1 | Q221: 1637.88 | U221: East | V221: Furniture | X221: EAST | Y221: FURNITURE | AA221: east | AB221: furniture
A222: 41aee1e8 | B222: 45010 | C222: s0uTH | D222: sports | E222: 2727.47 | F222: 35 | G222: 1 | H222: 1875.23 | I222: 41aee1e8 | J222: 45010 | K222: South | L222: Sports | M222: 2727.47 | N222: =VLOOKUP($K222,Sales_Performance_Analysis.csv!$S$1:$T$5,2,FALSE) -> 2478.5568 | O222: 35 | P222: 1 | Q222: 1875.23 | U222: South | V222: Sports | X222: SOUTH | Y222: SPORTS | AA222: south | AB222: sports
A223: 2f562dc0 | B223: 45275 | C223: s0uTH | D223: GrocerieS | E223: 1765.49 | F223: 13 | G223: 24 | H223: 1951.72 | I223: 2f562dc0 | J223: 45275 | K223: South | L223: Groceries | M223: 1765.49 | N223: =VLOOKUP($K223,Sales_Performance_Analysis.csv!$S$1:$T$5,2,FALSE) -> 2478.5568 | O223: 13 | P223: 24 | Q223: 1951.72 | U223: South | V223: Groceries | X223: SOUTH | Y223: GROCERIES | AA223: south | AB223: groceries
A224: 1790f693 | B224: 44947 | C224: norTh | D224: FURNiture | E224: 4383.76 | F224: 40 | G224: 21 | H224: 1013.33 | I224: 1790f693 | J224: 44947 | K224: North | L224: Furniture | M224: 4383.76 | N224: =VLOOKUP($K224,Sales_Performance_Analysis.csv!$S$1:$T$5,2,FALSE) -> 2573.1196 | O224: 40 | P224: 21 | Q224: 1013.33 | U224: North | V224: Furniture | X224: NORTH | Y224: FURNITURE | AA224: north | AB224: furniture
A225: 1ad9d5e9 | B225: 45476 | C225: s0uTH | D225: GrocerieS | E225: 4240.64 | F225: 49 | G225: 14 | H225: 1765.62 | I225: 1ad9d5e9 | J225: 45476 | K225: South | L225: Groceries | M225: 4240.64 | N225: =VLOOKUP($K225,Sales_Performance_Analysis.csv!$S$1:$T$5,2,FALSE) -> 2478.5568 | O225: 49 | P225: 14 | Q225: 1765.62 | U225: South | V225: Groceries | X225: SOUTH | Y225: GROCERIES | AA225: south | AB225: groceries
A226: ae129571 | B226: 44970 | C226: s0uTH | D226: FURNiture | E226: 273.84 | F226: 44 | G226: 29 | H226: 821 | I226: ae129571 | J226: 44970 | K226: South | L226: Furniture | M226: 273.84 | N226: =VLOOKUP($K226,Sales_Performance_Analysis.csv!$S$1:$T$5,2,FALSE) -> 2478.5568 | O226: 44 | P226: 29 | Q226: 821 | U226: South | V226: Furniture | X226: SOUTH | Y226: FURNITURE | AA226: south | AB226: furniture
A227: 79a06bc6 | B227: 45019 | C227: eAsT | D227: sports | E227: 152.53 | F227: 10 | G227: 16 | H227: 1958.8 | I227: 79a06bc6 | J227: 45019 | K227: East | L227: Sports | M227: 152.53 | N227: =VLOOKUP($K227,Sales_Performance_Analysis.csv!$S$1:$T$5,2,FALSE) -> 2529.8487 | O227: 10 | P227: 16 | Q227: 1958.8 | U227: East | V227: Sports | X227: EAST | Y227: SPORTS | AA227: east | AB227: sports
A228: 65240ae3 | B228: 45106 | C228: Messt | D228: GrocerieS | E228: 1407.97 | F228: 26 | G228: 35 | H228: 978.17 | I228: 65240ae3 | J228: 45106 | K228: East | L228: Groceries | M228: 1407.97 | N228: =VLOOKUP($K228,Sales_Performance_Analysis.csv!$S$1:$T$5,2,FALSE) -> 2529.8487 | O228: 26 | P228: 35 | Q228: 978.17 | U228: East | V228: Groceries | X228: EAST | Y228: GROCERIES | AA228: east | AB228: groceries
A229: d4df366c | B229: 45459 | C229: Messt | D229: FURNiture | E229: 4083.3 | F229: 22 | G229: 40 | H229: 1003.31 | I229: d4df366c | J229: 45459 | K229: East | L229: Furniture | M229: 4083.3 | N229: =VLOOKUP($K229,Sales_Performance_Analysis.csv!$S$1:$T$5,2,FALSE) -> 2529.8487 | O229: 22 | P229: 40 | Q229: 1003.31 | U229: East | V229: Furniture | X229: EAST | Y229: FURNITURE | AA229: east | AB229: furniture
... A271: d344a2c7 | B271: 45135 | C271: eAsT | D271: FURNiture | E271: 3012.88 | F271: 16 | G271: 16 | H271: 789.81 | I271: d344a2c7 | J271: 45135 | K271: East | L271: Furniture | M271: 3012.88 | N271: =VLOOKUP($K271,Sales_Performance_Analysis.csv!$S$1:$T$5,2,FALSE) -> 2529.8487 | O271: 16 | P271: 16 | Q271: 789.81 | U271: East | V271: Furniture | X271: EAST | Y271: FURNITURE | AA271: east | AB271: furniture
A272: 6.7765e+71 | B272: 44970 | C272: norTh | D272: Clothing | E272: 1877.37 | F272: 40 | G272: 46 | H272: 730.86 | I272: 6.7765e+71 | J272: 44970 | K272: North | L272: Clothing | M272: 1877.37 | N272: =VLOOKUP($K272,Sales_Performance_Analysis.csv!$S$1:$T$5,2,FALSE) -> 2573.1196 | O272: 40 | P272: 46 | Q272: 730.86 | U272: North | V272: Clothing | X272: NORTH | Y272: CLOTHING | AA272: north | AB272: clothing
A273: 3cccf911 | B273: 45595 | C273: Messt | D273: electronicS | E273: 2634.24 | F273: 19 | G273: 35 | H273: 38.85 | I273: 3cccf911 | J273: 45595 | K273: East | L273: Electronics | M273: 2634.24 | N273: =VLOOKUP($K273,Sales_Performance_Analysis.csv!$S$1:$T$5,2,FALSE) -> 2529.8487 | O273: 19 | P273: 35 | Q273: 38.85 | U273: East | V273: Electronics | X273: EAST | Y273: ELECTRONICS | AA273: east | AB273: electronics
A274: 7fc85b77 | B274: 45023 | C274: eAsT | D274: sports | E274: 2112.39 | F274: 29 | G274: 15 | H274: 1063.37 | I274: 7fc85b77 | J274: 45023 | K274: East | L274: Sports | M274: 2112.39 | N274: =VLOOKUP($K274,Sales_Performance_Analysis.csv!$S$1:$T$5,2,FALSE) -> 2529.8487 | O274: 29 | P274: 15 | Q274: 1063.37 | U274: East | V274: Sports | X274: EAST | Y274: SPORTS | AA274: east | AB274: sports
...

Sheet Task 1
A1: Order Date | B1: Clean Region | C1: Clean Category
A2: 45022 | B2: {=_xlfn.IFS(LEFT(Sales_Performance_Analysis.csv!C2:C4001,1)="N","North",LEFT(Sales_Performance_Analysis.csv!C2:C4001,1)="E","East",LEFT(Sales_Performance_Analysis.csv!C2:C4001,1)="M","East",LEFT(Sales_Performance_Analysis.csv!C2:C4001,1)="W","West",LEFT(Sales_Performance_Analysis.csv!C2:C4001,1)="S","South")} -> North | C2: {=_xlfn.IFS(LEFT(Sales_Performance_Analysis.csv!D2:D4001,1)="G","Groceries",LEFT(Sales_Performance_Analysis.csv!D2:D4001,1)="C","Clothing",LEFT(Sales_Performance_Analysis.csv!D2:D4001,1)="F","Furniture",LEFT(Sales_Performance_Analysis.csv!D2:D4001,1)="S","Sports",LEFT(Sales_Performance_Analysis.csv!D2:D4001,1)="E","Electronics")} -> Groceries
A3: 45412 | B3: East | C3: Groceries
A4: 45363 | B4: East | C4: Groceries
A5: 45331 | B5: East | C5: Groceries
A6: 45502 | B6: South | C6: Clothing
A7: 45164 | B7: East | C7: Furniture
A8: 45572 | B8: East | C8: Sports
A9: 45000 | B9: East | C9: Electronics
A10: 45106 | B10: East | C10: Clothing
A11: 44998 | B11: South | C11: Clothing
A12: 45439 | B12: East | C12: Groceries
A13: 45291 | B13: East | C13: Electronics
A14: 45239 | B14: East | C14: Sports
... A4001: 45465 | B4001: East | C4001: Furniture

Sheet Task 4
A1: Total sales for each Region | D1: Category | E1: Avg Dis % | F1: Avg Profit
A2: Region | B2: Sum of Sales | D2: Furniture | E2: =AVERAGEIF(Sales_Performance_Analysis.csv!L:L,"furniture",Sales_Performance_Analysis.csv!P:P) -> 25.230392 | F2: =AVERAGEIF(Sales_Performance_Analysis.csv!L:L,"Furniture",Sales_Performance_Analysis.csv!Q:Q) -> 1023.3827
A3: North | B3: =SUMIF(Sales_Performance_Analysis.csv!$K:$K,Sales_Performance_Analysis.csv!$S2,Sales_Performance_Analysis.csv!$M:$M) -> 2539669
A4: East | B4: =SUMIF(Sales_Performance_Analysis.csv!$K:$K,Sales_Performance_Analysis.csv!$S3,Sales_Performance_Analysis.csv!$M:$M) -> 2623453.1
A5: West | B5: =SUMIF(Sales_Performance_Analysis.csv!$K:$K,Sales_Performance_Analysis.csv!$S4,Sales_Performance_Analysis.csv!$M:$M) -> 2153328
A6: South | B6: =SUMIF(Sales_Performance_Analysis.csv!$K:$K,Sales_Performance_Analysis.csv!$S5,Sales_Performance_Analysis.csv!$M:$M) -> 2793333.5

Sheet Task 5
A1: Clean Category | B1: Clean Region | C1: Sum of Sales Amount | D1: Sum of Profit
A2: Clothing | C2: 2156007.6 | D2: 856347.49
B3: East | C3: 544147.05 | D3: 206173.43
B4: North | C4: 575975.88 | D4: 207145.82
B5: South | C5: 607267.41 | D5: 257012.1
B6: West | C6: 428617.24 | D6: 186016.14
A7: Electronics | C7: 2047834.9 | D7: 803657.96
B8: East | C8: 487335.04 | D8: 196771.53
B9: North | C9: 527159.55 | D9: 203772.53
B10: South | C10: 542960.29 | D10: 218587.48
B11: West | C11: 490380.05 | D11: 184526.42
A12: Furniture | C12: 2049496.2 | D12: 835080.32
B13: East | C13: 568091.34 | D13: 229622.02
B14: North | C14: 494993.63 | D14: 209391.78
B15: South | C15: 542353.65 | D15: 214936.91
B16: West | C16: 444057.54 | D16: 181129.61
A17: Groceries | C17: 1864225.1 | D17: 739605.38
B18: East | C18: 442386.15 | D18: 179081.18
B19: North | C19: 471913.51 | D19: 172529.97
B20: South | C20: 552437.15 | D20: 236904.15
B21: West | C21: 397488.25 | D21: 151090.08
A22: Sports | C22: 1992220 | D22: 797005.36
B23: East | C23: 581493.55 | D23: 223349.19
B24: North | C24: 469626.43 | D24: 177465.97
B25: South | C25: 548315.02 | D25: 228538.76
B26: West | C26: 392784.96 | D26: 167651.44
A27: Grand Total | C27: 10109784 | D27: 4031696.5

Sheet Bar Chart
A3: Clean Region | B3: Sum of Sales Amount
A4: East | B4: 2623453.1
A5: North | B5: 2539669
A6: South | B6: 2793333.5
A7: Grand Total | B7: 7956455.7

Sheet Pie Chart
A3: Clean Category | B3: Sum of Sales Amount
A4: Clothing | B4: 1727390.3
A5: Electronics | B5: 1557454.9
A6: Furniture | B6: 1605438.6
A7: Groceries | B7: 1466736.8
A8: Sports | B8: 1599435
A9: Grand Total | B9: 7956455.6

Sheet Stacked Bar Chart
A1: Sum of Sales Amount | B1: Clean Category
A2: Clean Region | B2: Clothing | C2: Electronics | D2: Furniture | E2: Groceries | F2: Sports | G2: Grand Total
A3: East | B3: 544147.05 | C3: 487335.04 | D3: 568091.34 | E3: 442386.15 | F3: 581493.55 | G3: 2623453.1
A4: North | B4: 575975.88 | C4: 527159.55 | D4: 494993.63 | E4: 471913.51 | F4: 469626.43 | G4: 2539669
A5: South | B5: 607267.41 | C5: 542960.29 | D5: 542353.65 | E5: 552437.15 | F5: 548315.02 | G5: 2793333.5
A6: Grand Total | B6: 1727390.3 | C6: 1557454.9 | D6: 1605438.6 | E6: 1466736.8 | F6: 1599435 | G6: 7956455.6

Sheet Dashboards
IC10: Sales Performance Dashboard
KK57: =SUM(Sales_Performance_Analysis.csv!O2:O4001) -> 102791 | NY57: =SUM(Sales_Performance_Analysis.csv!Q2:Q4001) -> 4031696.5
GS58: =SUM(Sales_Performance_Analysis.csv!M2:M4001) -> 10109784

Sheet Task 10
A1: Sales Amount | B1: Profit | C1: Profit Margin%
A2: 859.29 | B2: 1653.87 | C2: {=(B2:B4001/A2:A4001)*100} -> 192.46936
A3: 1546.81 | B3: 1932.71 | C3: 124.94812
A4: 4703.58 | B4: 527.47 | C4: 11.214224
A5: 3377.17 | B5: 482.65 | C5: 14.291552
A6: 3517.49 | B6: 748.72 | C6: 21.285633
A7: 362.55 | B7: 314.71 | C7: 86.804579
A8: 4811.17 | B8: 1372.89 | C8: 28.535471
A9: 3565.2 | B9: 1437.3 | C9: 40.314709
A10: 3805.25 | B10: 1537.28 | C10: 40.398923
A11: 2178.72 | B11: 1696.65 | C11: 77.873706
A12: 2844.93 | B12: 1166.39 | C12: 40.9989
A13: 3600.04 | B13: 1632.75 | C13: 45.353663
A14: 941.88 | B14: 646.49 | C14: 68.638255
... A4001: 2975.86 | B4001: 1870.61 | C4001: 62.859476
